Metadata-Version: 2.1
Name: hack4u_proyecto-proyecto
Version: 0.2.0
Summary: Una biblioteca para consultar cursos de hack4u.
Home-page: https://hack4u.io
Author: Marcelo
